protein_domain_segmentation/__init__.py
protein_domain_segmentation/version.py
protein_domain_segmentation/chainsaw/__init__.py
protein_domain_segmentation/chainsaw/constants.py
protein_domain_segmentation/chainsaw/domain_chop.py
protein_domain_segmentation/chainsaw/errors.py
protein_domain_segmentation/chainsaw/factories.py
protein_domain_segmentation/chainsaw/featurisers.py
protein_domain_segmentation/chainsaw/run_chainsaw.py
protein_domain_segmentation/chainsaw/domain_assignment/__init__.py
protein_domain_segmentation/chainsaw/domain_assignment/assigners.py
protein_domain_segmentation/chainsaw/domain_assignment/sparse_lowrank.py
protein_domain_segmentation/chainsaw/domain_assignment/util.py
protein_domain_segmentation/chainsaw/models/__init__.py
protein_domain_segmentation/chainsaw/models/results.py
protein_domain_segmentation/chainsaw/models/rosetta.py
protein_domain_segmentation/chainsaw/stride/stride
protein_domain_segmentation/chainsaw/utils/__init__.py
protein_domain_segmentation/chainsaw/utils/common.py
protein_domain_segmentation/chainsaw/utils/domain_boundary_distance_score.py
protein_domain_segmentation/chainsaw/utils/ndo_score.py
protein_domain_segmentation/chainsaw/utils/pdb_reres.py
protein_domain_segmentation/chainsaw/utils/secondary_structure.py
protein_domain_segmentation/chainsaw/weights/config.json
protein_domain_segmentation/chainsaw/weights/feature_config.json
protein_domain_segmentation/chainsaw/weights/weights.pt
protein_domain_segmentation/merizo/__init__.py
protein_domain_segmentation/merizo/run_merizo.py
protein_domain_segmentation/merizo/model/__init__.py
protein_domain_segmentation/merizo/model/network.py
protein_domain_segmentation/merizo/model/decoders/__init__.py
protein_domain_segmentation/merizo/model/decoders/mask_decoder.py
protein_domain_segmentation/merizo/model/ipa/__init__.py
protein_domain_segmentation/merizo/model/ipa/ipa_encoder.py
protein_domain_segmentation/merizo/model/ipa/nndef_ipa.py
protein_domain_segmentation-0.1.4.dist-info/licenses/LICENSE
protein_domain_segmentation-0.1.4.dist-info/METADATA
protein_domain_segmentation-0.1.4.dist-info/WHEEL
protein_domain_segmentation-0.1.4.dist-info/top_level.txt
protein_domain_segmentation-0.1.4.dist-info/RECORD
