Metadata-Version: 2.4
Name: protein_domain_segmentation
Version: 0.1.4
Summary: A library for protein domain segmentation using Merizo and Chainsaw.
Author-email: Gaspard Merten <gaspard.mp.work@gmail.com>
License: MIT License
Project-URL: Homepage, https://github.com/GaspardMerten/protein-domain-segmentation-library
Project-URL: Issues, https://github.com/GaspardMerten/protein-domain-segmentation-library/issues
Classifier: Development Status :: 4 - Beta
Classifier: Intended Audience :: Science/Research
Classifier: Topic :: Scientific/Engineering :: Bio-Informatics
Classifier: Programming Language :: Python :: 3
Classifier: Programming Language :: Python :: 3.8
Classifier: Programming Language :: Python :: 3.9
Classifier: Programming Language :: Python :: 3.10
Classifier: Programming Language :: Python :: 3.11
Classifier: License :: OSI Approved :: MIT License
Classifier: Operating System :: OS Independent
Requires-Python: >=3.10
License-File: LICENSE
Requires-Dist: torch
Requires-Dist: MDAnalysis
Requires-Dist: pandas
Requires-Dist: biopython
Requires-Dist: pydantic
Requires-Dist: einops
Requires-Dist: natsort
Requires-Dist: rotary_embedding_torch
Dynamic: license-file
